wikidataloader/__init__.py
wikidataloader/wikidataloader.py
wikidataloader-0.0.6.dist-info/licenses/LICENSE.txt
wikidataloader-0.0.6.dist-info/METADATA
wikidataloader-0.0.6.dist-info/WHEEL
wikidataloader-0.0.6.dist-info/top_level.txt
wikidataloader-0.0.6.dist-info/RECORD
