Metadata-Version: 2.4
Name: wikidataloader
Version: 0.0.6
Summary: Pythonic wrapper around the Wikidata SPARQL API for quick creation of datasets from Wikidata
Author-email: Nizar <nizar.neezr@web.de>
License-Expression: GPL-3.0-or-later
Project-URL: Homepage, https://github.com/neezr/wikidataloader
Project-URL: Issues, https://github.com/neezr/wikidataloader/issues
Project-URL: Repository, https://github.com/neezr/wikidataloader.git
Keywords: datasets,wikidata,sparql
Classifier: Development Status :: 5 - Production/Stable
Classifier: Programming Language :: Python :: 3
Classifier: Operating System :: OS Independent
Classifier: Intended Audience :: Science/Research
Classifier: Topic :: Scientific/Engineering :: Artificial Intelligence
Requires-Python: >=3.9
License-File: LICENSE.txt
Requires-Dist: requests
Requires-Dist: pandas
Dynamic: license-file
